aidot/__init__.py
aidot/aes_utils.py
aidot/discover.py
aidot/lan.py
aidot/login_const.py
aidot/login_control.py
aidot/login_data.py
aidot-0.1.1.dist-info/LICENSE
aidot-0.1.1.dist-info/METADATA
aidot-0.1.1.dist-info/WHEEL
aidot-0.1.1.dist-info/top_level.txt
aidot-0.1.1.dist-info/RECORD
