Metadata-Version: 2.1
Name: aidot
Version: 0.1.1
Summary: aidot control wifi lights
Author: aidotdev2024
Classifier: Programming Language :: Python :: 3.11
Classifier: License :: OSI Approved :: MIT License
Classifier: Operating System :: OS Independent
License-File: LICENSE
Requires-Dist: requests
Requires-Dist: aiohttp
Requires-Dist: setuptools
